mcp_server_hatena_weekly/__init__.py
mcp_server_hatena_weekly/server.py
mcp_server_hatena_weekly/data/month/2023-01.json
mcp_server_hatena_weekly/data/month/2023-02.json
mcp_server_hatena_weekly/data/month/2023-03.json
mcp_server_hatena_weekly/data/month/2023-04.json
mcp_server_hatena_weekly/data/month/2023-05.json
mcp_server_hatena_weekly/data/month/2023-06.json
mcp_server_hatena_weekly/data/month/2023-07.json
mcp_server_hatena_weekly/data/month/2023-08.json
mcp_server_hatena_weekly/data/month/2023-09.json
mcp_server_hatena_weekly/data/month/2023-10.json
mcp_server_hatena_weekly/data/month/2023-11.json
mcp_server_hatena_weekly/data/month/2024-01.json
mcp_server_hatena_weekly/data/month/2024-02.json
mcp_server_hatena_weekly/data/month/2024-03.json
mcp_server_hatena_weekly/data/month/2024-04.json
mcp_server_hatena_weekly/data/month/2024-05.json
mcp_server_hatena_weekly/data/month/2024-06.json
mcp_server_hatena_weekly/data/month/2024-07.json
mcp_server_hatena_weekly/data/month/2024-08.json
mcp_server_hatena_weekly/data/month/2024-09.json
mcp_server_hatena_weekly/data/month/2024-10.json
mcp_server_hatena_weekly/data/month/2024-11.json
mcp_server_hatena_weekly/data/month/2024-12.json
mcp_server_hatena_weekly/data/month/2025-01.json
mcp_server_hatena_weekly/data/month/2025-02.json
mcp_server_hatena_weekly/data/month/2025-03.json
mcp_server_hatena_weekly/data/month/2025-04.json
mcp_server_hatena_weekly/data/month/2025-05.json
mcp_server_hatena_weekly/data/week/2023-01-1.json
mcp_server_hatena_weekly/data/week/2023-01-2.json
mcp_server_hatena_weekly/data/week/2023-01-3.json
mcp_server_hatena_weekly/data/week/2023-01-4.json
mcp_server_hatena_weekly/data/week/2023-01-5.json
mcp_server_hatena_weekly/data/week/2023-02-1.json
mcp_server_hatena_weekly/data/week/2023-02-2.json
mcp_server_hatena_weekly/data/week/2023-02-3.json
mcp_server_hatena_weekly/data/week/2023-02-4.json
mcp_server_hatena_weekly/data/week/2023-03-1.json
mcp_server_hatena_weekly/data/week/2023-03-2.json
mcp_server_hatena_weekly-0.1.4.dist-info/METADATA
mcp_server_hatena_weekly-0.1.4.dist-info/WHEEL
mcp_server_hatena_weekly-0.1.4.dist-info/entry_points.txt
mcp_server_hatena_weekly-0.1.4.dist-info/RECORD
