Metadata-Version: 2.4
Name: mcp-server-hatena-weekly
Version: 0.1.4
Summary: Hatena Bookmark Weekly/Monthly Ranking MCP server for fetching popular bookmarks
Author-email: yareyaredesuyo <yareyaredesuyo@gmail.com>
License-Expression: MIT
Keywords: bookmark,hatena,llm,mcp,model-context-protocol,ranking
Classifier: Development Status :: 4 - Beta
Classifier: Intended Audience :: Developers
Classifier: License :: OSI Approved :: MIT License
Classifier: Programming Language :: Python :: 3
Classifier: Programming Language :: Python :: 3.10
Classifier: Topic :: Internet :: WWW/HTTP :: Indexing/Search
Classifier: Topic :: Software Development :: Libraries :: Python Modules
Requires-Python: >=3.10
Requires-Dist: beautifulsoup4>=4.9.0
Requires-Dist: fastmcp>=2.5.2
Requires-Dist: pydantic>=2.0.0
Requires-Dist: requests>=2.25.0
